{"document": [{"id": 0, "box": [27, 128, 224, 146], "text": "United States Corporation Company", "words": [{"box": [27, 131, 65, 145], "id": 0, "text": "United"}, {"box": [67, 133, 102, 146], "id": 1, "text": "States"}, {"box": [102, 130, 169, 144], "id": 2, "text": "Corporation"}, {"box": [172, 128, 224, 145], "id": 3, "text": "Company"}]}, {"id": 1, "box": [27, 155, 63, 172], "text": "DATE:", "words": [{"box": [27, 155, 63, 172], "id": 4, "text": "DATE:"}]}, {"id": 2, "box": [28, 183, 50, 197], "text": "TO:", "words": [{"box": [28, 183, 50, 197], "id": 5, "text": "TO:"}]}, {"id": 3, "box": [28, 284, 52, 299], "text": "RE:", "words": [{"box": [28, 284, 52, 299], "id": 6, "text": "RE:"}]}, {"id": 4, "box": [31, 559, 140, 574], "text": "TITLE OF ACTION:", "words": [{"box": [31, 559, 66, 574], "id": 7, "text": "TITLE"}, {"box": [68, 560, 85, 573], "id": 8, "text": "OF"}, {"box": [91, 560, 140, 574], "id": 9, "text": "ACTION:"}]}, {"id": 5, "box": [31, 591, 49, 602], "text": "vs.", "words": [{"box": [31, 591, 49, 602], "id": 10, "text": "vs."}]}, {"id": 6, "box": [31, 634, 187, 649], "text": "COURT OR JURISDICTION", "words": [{"box": [31, 634, 77, 649], "id": 11, "text": "COURT"}, {"box": [78, 634, 99, 649], "id": 12, "text": "OR"}, {"box": [99, 634, 187, 649], "id": 13, "text": "JURISDICTION"}]}, {"id": 7, "box": [31, 677, 158, 694], "text": "Tel Call Placed Direct", "words": [{"box": [31, 677, 51, 691], "id": 14, "text": "Tel"}, {"box": [53, 679, 75, 693], "id": 15, "text": "Call"}, {"box": [77, 677, 118, 694], "id": 16, "text": "Placed"}, {"box": [124, 677, 158, 690], "id": 17, "text": "Direct"}]}, {"id": 8, "box": [31, 743, 201, 759], "text": "ATTORNEYS FOR CLAIMANT", "words": [{"box": [31, 744, 105, 759], "id": 18, "text": "ATTORNEYS"}, {"box": [109, 744, 136, 758], "id": 19, "text": "FOR"}, {"box": [138, 743, 201, 758], "id": 20, "text": "CLAIMANT"}]}, {"id": 9, "box": [31, 873, 673, 896], "text": "PLEASE ACKNOWLEDGE RECEIPT OF THIS NOTICE AND THE ENCLOSURES BY SIGNING AND RETURNING THE", "words": [{"box": [31, 883, 81, 896], "id": 21, "text": "PLEASE"}, {"box": [82, 881, 180, 895], "id": 22, "text": "ACKNOWLEDGE"}, {"box": [182, 878, 235, 893], "id": 23, "text": "RECEIPT"}, {"box": [236, 878, 253, 892], "id": 24, "text": "OF"}, {"box": [254, 878, 283, 892], "id": 25, "text": "THIS"}, {"box": [284, 877, 333, 892], "id": 26, "text": "NOTICE"}, {"box": [332, 878, 360, 889], "id": 27, "text": "AND"}, {"box": [360, 877, 385, 891], "id": 28, "text": "THE"}, {"box": [388, 877, 470, 890], "id": 29, "text": "ENCLOSURES"}, {"box": [473, 877, 493, 890], "id": 30, "text": "BY"}, {"box": [494, 874, 544, 892], "id": 31, "text": "SIGNING"}, {"box": [546, 873, 574, 888], "id": 32, "text": "AND"}, {"box": [574, 873, 645, 891], "id": 33, "text": "RETURNING"}, {"box": [648, 874, 673, 889], "id": 34, "text": "THE"}]}, {"id": 10, "box": [31, 926, 114, 940], "text": "Date Received:", "words": [{"box": [31, 926, 58, 940], "id": 35, "text": "Date"}, {"box": [60, 926, 114, 940], "id": 36, "text": "Received:"}]}, {"id": 11, "box": [32, 655, 119, 670], "text": "RETURN DATE", "words": [{"box": [32, 655, 82, 670], "id": 37, "text": "RETURN"}, {"box": [85, 656, 119, 670], "id": 38, "text": "DATE"}]}, {"id": 12, "box": [32, 697, 107, 712], "text": "COMMENTS:", "words": [{"box": [32, 697, 107, 712], "id": 39, "text": "COMMENTS:"}]}, {"id": 13, "box": [32, 823, 239, 837], "text": "PAPERS TRANSMITTED TO CLIENT", "words": [{"box": [32, 824, 84, 837], "id": 40, "text": "PAPERS"}, {"box": [88, 823, 172, 837], "id": 41, "text": "TRANSMITTED"}, {"box": [175, 824, 193, 835], "id": 42, "text": "TO"}, {"box": [196, 824, 239, 834], "id": 43, "text": "CLIENT"}]}, {"id": 14, "box": [32, 851, 67, 865], "text": "Other", "words": [{"box": [32, 851, 67, 865], "id": 44, "text": "Other"}]}, {"id": 15, "box": [32, 890, 580, 912], "text": "DUPLICATE COPY A BUSINESS REPLY ENVELOPE IS ENCLOSED FOR YOUR CONVENIENCE", "words": [{"box": [32, 897, 99, 912], "id": 45, "text": "DUPLICATE"}, {"box": [103, 897, 139, 910], "id": 46, "text": "COPY"}, {"box": [142, 895, 155, 910], "id": 47, "text": "A"}, {"box": [158, 894, 218, 911], "id": 48, "text": "BUSINESS"}, {"box": [222, 894, 260, 908], "id": 49, "text": "REPLY"}, {"box": [264, 892, 331, 907], "id": 50, "text": "ENVELOPE"}, {"box": [334, 892, 347, 905], "id": 51, "text": "IS"}, {"box": [349, 891, 415, 905], "id": 52, "text": "ENCLOSED"}, {"box": [419, 892, 447, 905], "id": 53, "text": "FOR"}, {"box": [450, 891, 486, 904], "id": 54, "text": "YOUR"}, {"box": [489, 890, 580, 904], "id": 55, "text": "CONVENIENCE"}]}, {"id": 16, "box": [34, 838, 68, 852], "text": "Fed X", "words": [{"box": [34, 838, 58, 852], "id": 56, "text": "Fed"}, {"box": [57, 838, 68, 851], "id": 57, "text": "X"}]}, {"id": 17, "box": [38, 378, 355, 395], "text": "as registered agent for the above- captioned corporation on", "words": [{"box": [38, 384, 53, 394], "id": 58, "text": "as"}, {"box": [56, 381, 110, 395], "id": 59, "text": "registered"}, {"box": [113, 381, 145, 395], "id": 60, "text": "agent"}, {"box": [147, 381, 162, 394], "id": 61, "text": "for"}, {"box": [165, 380, 183, 393], "id": 62, "text": "the"}, {"box": [186, 380, 224, 393], "id": 63, "text": "above-"}, {"box": [223, 380, 275, 393], "id": 64, "text": "captioned"}, {"box": [277, 380, 338, 393], "id": 65, "text": "corporation"}, {"box": [341, 378, 355, 392], "id": 66, "text": "on"}]}, {"id": 18, "box": [49, 508, 62, 522], "text": "X", "words": [{"box": [49, 508, 62, 522], "id": 67, "text": "X"}]}, {"id": 19, "box": [52, 335, 393, 352], "text": "We enclose the following documents which were served upon:", "words": [{"box": [52, 337, 72, 352], "id": 68, "text": "We"}, {"box": [74, 338, 117, 351], "id": 69, "text": "enclose"}, {"box": [122, 337, 139, 350], "id": 70, "text": "the"}, {"box": [142, 337, 189, 352], "id": 71, "text": "following"}, {"box": [191, 335, 252, 348], "id": 72, "text": "documents"}, {"box": [256, 335, 285, 348], "id": 73, "text": "which"}, {"box": [289, 337, 316, 348], "id": 74, "text": "were"}, {"box": [320, 335, 356, 348], "id": 75, "text": "served"}, {"box": [359, 335, 393, 348], "id": 76, "text": "upon:"}]}, {"id": 20, "box": [68, 432, 124, 447], "text": "Summons", "words": [{"box": [68, 432, 124, 447], "id": 77, "text": "Summons"}]}, {"id": 21, "box": [68, 453, 124, 466], "text": "Complaint", "words": [{"box": [68, 453, 124, 466], "id": 78, "text": "Complaint"}]}, {"id": 22, "box": [70, 468, 249, 486], "text": "Duplicate copies of the Notice and", "words": [{"box": [70, 471, 119, 486], "id": 79, "text": "Duplicate"}, {"box": [122, 471, 158, 485], "id": 80, "text": "copies"}, {"box": [158, 472, 171, 485], "id": 81, "text": "of"}, {"box": [172, 471, 190, 482], "id": 82, "text": "the"}, {"box": [190, 469, 226, 482], "id": 83, "text": "Notice"}, {"box": [228, 468, 249, 483], "id": 84, "text": "and"}]}, {"id": 23, "box": [68, 489, 220, 504], "text": "Acknowledgement enclosed", "words": [{"box": [68, 489, 167, 504], "id": 85, "text": "Acknowledgement"}, {"box": [170, 489, 220, 502], "id": 86, "text": "enclosed"}]}, {"id": 24, "box": [68, 510, 104, 523], "text": "Other:", "words": [{"box": [68, 510, 104, 523], "id": 87, "text": "Other:"}]}, {"id": 25, "box": [87, 152, 146, 167], "text": "12- 13- 89", "words": [{"box": [87, 152, 109, 167], "id": 88, "text": "12-"}, {"box": [109, 152, 131, 166], "id": 89, "text": "13-"}, {"box": [131, 152, 146, 167], "id": 90, "text": "89"}]}, {"id": 26, "box": [87, 180, 195, 196], "text": "LORILLARD, INC.", "words": [{"box": [87, 183, 160, 196], "id": 91, "text": "LORILLARD,"}, {"box": [166, 180, 195, 194], "id": 92, "text": "INC."}]}, {"id": 27, "box": [88, 194, 254, 210], "text": "ONE PARK AVENUE 18TH FL", "words": [{"box": [88, 198, 110, 209], "id": 93, "text": "ONE"}, {"box": [117, 197, 146, 210], "id": 94, "text": "PARK"}, {"box": [152, 196, 197, 209], "id": 95, "text": "AVENUE"}, {"box": [203, 194, 234, 207], "id": 96, "text": "18TH"}, {"box": [237, 194, 254, 207], "id": 97, "text": "FL"}]}, {"id": 28, "box": [88, 209, 235, 225], "text": "NEW YORK, N. Y. 10016", "words": [{"box": [88, 211, 112, 225], "id": 98, "text": "NEW"}, {"box": [116, 212, 152, 223], "id": 99, "text": "YORK,"}, {"box": [158, 211, 173, 225], "id": 100, "text": "N."}, {"box": [173, 211, 187, 224], "id": 101, "text": "Y."}, {"box": [197, 209, 235, 222], "id": 102, "text": "10016"}]}, {"id": 29, "box": [88, 216, 398, 241], "text": "ATTN: MR. ARTHUR STEVENS, ESQ A. J. STEVENS", "words": [{"box": [88, 228, 126, 241], "id": 103, "text": "ATTN:"}, {"box": [131, 226, 153, 239], "id": 104, "text": "MR."}, {"box": [158, 223, 204, 240], "id": 105, "text": "ARTHUR"}, {"box": [209, 223, 266, 238], "id": 106, "text": "STEVENS,"}, {"box": [274, 222, 302, 236], "id": 107, "text": "ESQ"}, {"box": [302, 219, 316, 234], "id": 108, "text": "A."}, {"box": [318, 218, 332, 233], "id": 109, "text": "J."}, {"box": [335, 216, 398, 233], "id": 110, "text": "STEVENS"}]}, {"id": 30, "box": [88, 275, 199, 292], "text": "LORILLARD, INC.", "words": [{"box": [88, 277, 161, 292], "id": 111, "text": "LORILLARD,"}, {"box": [168, 275, 199, 288], "id": 112, "text": "INC."}]}, {"id": 31, "box": [94, 591, 360, 615], "text": "R. J. REYNOLDS TOBACCO COMPANY, ET AL", "words": [{"box": [94, 599, 111, 613], "id": 113, "text": "R."}, {"box": [115, 598, 135, 615], "id": 114, "text": "J."}, {"box": [138, 598, 198, 612], "id": 115, "text": "REYNOLDS"}, {"box": [203, 596, 255, 613], "id": 116, "text": "TOBACCO"}, {"box": [260, 594, 317, 612], "id": 117, "text": "COMPANY,"}, {"box": [325, 594, 340, 609], "id": 118, "text": "ET"}, {"box": [345, 591, 360, 608], "id": 119, "text": "AL"}]}, {"id": 32, "box": [98, 841, 112, 856], "text": "X", "words": [{"box": [98, 841, 112, 856], "id": 120, "text": "X"}]}, {"id": 33, "box": [130, 500, 391, 519], "text": "CITATION AND FIRST ORIGINAL PETITION", "words": [{"box": [130, 506, 187, 519], "id": 121, "text": "CITATION"}, {"box": [194, 504, 216, 518], "id": 122, "text": "AND"}, {"box": [222, 504, 260, 518], "id": 123, "text": "FIRST"}, {"box": [263, 501, 326, 515], "id": 124, "text": "ORIGINAL"}, {"box": [330, 500, 391, 514], "id": 125, "text": "PETITION"}]}, {"id": 34, "box": [133, 88, 563, 115], "text": "PRENTICE HALL CORPORATE SERVICES", "words": [{"box": [133, 94, 241, 115], "id": 126, "text": "PRENTICE"}, {"box": [247, 94, 306, 115], "id": 127, "text": "HALL"}, {"box": [313, 92, 447, 114], "id": 128, "text": "CORPORATE"}, {"box": [455, 88, 563, 112], "id": 129, "text": "SERVICES"}]}, {"id": 35, "box": [138, 348, 500, 368], "text": "UNITED STATES CORPORATION COMPANY IN TEXAS", "words": [{"box": [138, 353, 192, 368], "id": 130, "text": "UNITED"}, {"box": [197, 352, 251, 366], "id": 131, "text": "STATES"}, {"box": [256, 349, 355, 364], "id": 132, "text": "CORPORATION"}, {"box": [359, 349, 422, 362], "id": 133, "text": "COMPANY"}, {"box": [429, 348, 447, 363], "id": 134, "text": "IN"}, {"box": [454, 348, 500, 362], "id": 135, "text": "TEXAS"}]}, {"id": 36, "box": [138, 401, 230, 417], "text": "Personal Service", "words": [{"box": [138, 402, 187, 417], "id": 136, "text": "Personal"}, {"box": [187, 401, 230, 415], "id": 137, "text": "Service"}]}, {"id": 37, "box": [144, 911, 278, 954], "text": "12/ 14/ 89", "words": [{"box": [144, 915, 191, 954], "id": 138, "text": "12/"}, {"box": [184, 911, 241, 953], "id": 139, "text": "14/"}, {"box": [235, 915, 278, 954], "id": 140, "text": "89"}]}, {"id": 38, "box": [147, 642, 434, 662], "text": "Monday next 20 days from date of service", "words": [{"box": [147, 651, 192, 662], "id": 141, "text": "Monday"}, {"box": [197, 649, 226, 660], "id": 142, "text": "next"}, {"box": [230, 648, 247, 659], "id": 143, "text": "20"}, {"box": [254, 648, 282, 661], "id": 144, "text": "days"}, {"box": [289, 645, 321, 658], "id": 145, "text": "from"}, {"box": [327, 645, 356, 658], "id": 146, "text": "date"}, {"box": [362, 645, 377, 656], "id": 147, "text": "of"}, {"box": [384, 642, 434, 655], "id": 148, "text": "service"}]}, {"id": 39, "box": [148, 837, 202, 851], "text": "Reg Mail", "words": [{"box": [148, 837, 173, 851], "id": 149, "text": "Reg"}, {"box": [177, 838, 202, 849], "id": 150, "text": "Mail"}]}, {"id": 40, "box": [151, 54, 544, 75], "text": "1 GULF+ WESTE PLAZA . NEW YORK, NEW YORK 23- 7773", "words": [{"box": [151, 61, 161, 74], "id": 151, "text": "1"}, {"box": [163, 61, 204, 75], "id": 152, "text": "GULF+"}, {"box": [205, 59, 244, 74], "id": 153, "text": "WESTE"}, {"box": [267, 57, 309, 72], "id": 154, "text": "PLAZA"}, {"box": [317, 60, 325, 71], "id": 155, "text": "."}, {"box": [332, 56, 361, 71], "id": 156, "text": "NEW"}, {"box": [365, 57, 404, 71], "id": 157, "text": "YORK,"}, {"box": [406, 54, 437, 71], "id": 158, "text": "NEW"}, {"box": [440, 56, 474, 70], "id": 159, "text": "YORK"}, {"box": [497, 57, 515, 70], "id": 160, "text": "23-"}, {"box": [513, 56, 544, 69], "id": 161, "text": "7773"}]}, {"id": 41, "box": [162, 296, 295, 311], "text": "(Represented Company)", "words": [{"box": [162, 296, 236, 311], "id": 162, "text": "(Represented"}, {"box": [239, 296, 295, 310], "id": 163, "text": "Company)"}]}, {"id": 42, "box": [172, 560, 269, 574], "text": "WEBSTER CRECC", "words": [{"box": [172, 561, 226, 574], "id": 164, "text": "WEBSTER"}, {"box": [230, 560, 269, 573], "id": 165, "text": "CRECC"}]}, {"id": 43, "box": [194, 673, 233, 690], "text": "Collect", "words": [{"box": [194, 673, 233, 690], "id": 166, "text": "Collect"}]}, {"id": 44, "box": [204, 624, 543, 646], "text": "345th Judicial District Court Travis County. Tx", "words": [{"box": [204, 631, 239, 646], "id": 167, "text": "345th"}, {"box": [246, 631, 305, 646], "id": 168, "text": "Judicial"}, {"box": [309, 630, 369, 644], "id": 169, "text": "District"}, {"box": [376, 627, 412, 642], "id": 170, "text": "Court"}, {"box": [418, 626, 464, 641], "id": 171, "text": "Travis"}, {"box": [469, 626, 519, 641], "id": 172, "text": "County."}, {"box": [525, 624, 543, 639], "id": 173, "text": "Tx"}]}, {"id": 45, "box": [209, 736, 328, 754], "text": "Mary Ellen Felps", "words": [{"box": [209, 737, 243, 752], "id": 174, "text": "Mary"}, {"box": [247, 737, 286, 754], "id": 175, "text": "Ellen"}, {"box": [292, 736, 328, 753], "id": 176, "text": "Felps"}]}, {"id": 46, "box": [214, 751, 313, 766], "text": "1000 West Ave.", "words": [{"box": [214, 751, 242, 765], "id": 177, "text": "1000"}, {"box": [249, 753, 281, 764], "id": 178, "text": "West"}, {"box": [284, 753, 313, 766], "id": 179, "text": "Ave."}]}, {"id": 47, "box": [212, 764, 338, 781], "text": "Austin, Tx. 78701", "words": [{"box": [212, 767, 262, 781], "id": 180, "text": "Austin,"}, {"box": [270, 767, 292, 780], "id": 181, "text": "Tx."}, {"box": [299, 764, 338, 778], "id": 182, "text": "78701"}]}, {"id": 48, "box": [244, 317, 475, 332], "text": "NOTICE OF SERVICE OF PROCESS", "words": [{"box": [244, 318, 297, 332], "id": 183, "text": "NOTICE"}, {"box": [300, 318, 321, 332], "id": 184, "text": "OF"}, {"box": [324, 317, 384, 331], "id": 185, "text": "SERVICE"}, {"box": [387, 318, 405, 331], "id": 186, "text": "OF"}, {"box": [408, 317, 475, 331], "id": 187, "text": "PROCESS"}]}, {"id": 49, "box": [249, 401, 257, 414], "text": "x", "words": [{"box": [249, 401, 257, 414], "id": 188, "text": "x"}]}, {"id": 50, "box": [272, 676, 323, 690], "text": "Spoke to", "words": [{"box": [272, 676, 307, 690], "id": 189, "text": "Spoke"}, {"box": [310, 676, 323, 689], "id": 190, "text": "to"}]}, {"id": 51, "box": [278, 399, 352, 415], "text": "Mail: Regular", "words": [{"box": [278, 401, 306, 415], "id": 191, "text": "Mail:"}, {"box": [309, 399, 352, 414], "id": 192, "text": "Regular"}]}, {"id": 52, "box": [293, 152, 398, 176], "text": "RECEIVED", "words": [{"box": [293, 152, 398, 176], "id": 193, "text": "RECEIVED"}]}, {"id": 53, "box": [299, 35, 392, 51], "text": "Executive Offices", "words": [{"box": [299, 36, 352, 51], "id": 194, "text": "Executive"}, {"box": [356, 35, 392, 50], "id": 195, "text": "Offices"}]}, {"id": 54, "box": [306, 73, 389, 87], "text": "(212) 373- 7500", "words": [{"box": [306, 74, 335, 87], "id": 196, "text": "(212)"}, {"box": [338, 73, 362, 87], "id": 197, "text": "373-"}, {"box": [360, 73, 389, 86], "id": 198, "text": "7500"}]}, {"id": 55, "box": [306, 187, 393, 209], "text": "DEC 14 89", "words": [{"box": [306, 189, 328, 209], "id": 199, "text": "DEC"}, {"box": [338, 187, 363, 205], "id": 200, "text": "14"}, {"box": [372, 187, 393, 208], "id": 201, "text": "89"}]}, {"id": 56, "box": [317, 429, 458, 444], "text": "A self- addressed stamped", "words": [{"box": [317, 430, 325, 443], "id": 202, "text": "A"}, {"box": [328, 430, 352, 443], "id": 203, "text": "self-"}, {"box": [351, 429, 407, 444], "id": 204, "text": "addressed"}, {"box": [406, 429, 458, 443], "id": 205, "text": "stamped"}]}, {"id": 57, "box": [316, 448, 420, 463], "text": "envelope enclosed", "words": [{"box": [316, 448, 369, 463], "id": 206, "text": "envelope"}, {"box": [370, 448, 420, 462], "id": 207, "text": "enclosed"}]}, {"id": 58, "box": [317, 468, 388, 481], "text": "Garnishment", "words": [{"box": [317, 468, 388, 481], "id": 208, "text": "Garnishment"}]}, {"id": 59, "box": [317, 485, 453, 502], "text": "Notice of Attorney's Lien", "words": [{"box": [317, 486, 352, 500], "id": 209, "text": "Notice"}, {"box": [356, 486, 369, 500], "id": 210, "text": "of"}, {"box": [370, 486, 424, 500], "id": 211, "text": "Attorney's"}, {"box": [426, 485, 453, 502], "id": 212, "text": "Lien"}]}, {"id": 60, "box": [342, 943, 399, 960], "text": "ORIGINAL", "words": [{"box": [342, 943, 399, 960], "id": 213, "text": "ORIGINAL"}]}, {"id": 61, "box": [352, 846, 483, 861], "text": "FORM PREPARED BY", "words": [{"box": [352, 848, 391, 861], "id": 214, "text": "FORM"}, {"box": [394, 846, 462, 860], "id": 215, "text": "PREPARED"}, {"box": [465, 846, 483, 861], "id": 216, "text": "BY"}]}, {"id": 62, "box": [362, 377, 421, 391], "text": "12- 13- 89", "words": [{"box": [362, 377, 386, 391], "id": 217, "text": "12-"}, {"box": [387, 377, 407, 391], "id": 218, "text": "13-"}, {"box": [406, 377, 421, 391], "id": 219, "text": "89"}]}, {"id": 63, "box": [374, 556, 381, 571], "text": ")", "words": [{"box": [374, 556, 381, 571], "id": 220, "text": ")"}]}, {"id": 64, "box": [374, 570, 382, 584], "text": ")", "words": [{"box": [374, 570, 382, 584], "id": 221, "text": ")"}]}, {"id": 65, "box": [374, 584, 381, 599], "text": ")", "words": [{"box": [374, 584, 381, 599], "id": 222, "text": ")"}]}, {"id": 66, "box": [374, 595, 381, 612], "text": ")", "words": [{"box": [374, 595, 381, 612], "id": 223, "text": ")"}]}, {"id": 67, "box": [406, 399, 470, 412], "text": "or Certified", "words": [{"box": [406, 401, 419, 412], "id": 224, "text": "or"}, {"box": [423, 399, 470, 412], "id": 225, "text": "Certified"}]}, {"id": 68, "box": [433, 378, 453, 389], "text": "via:", "words": [{"box": [433, 378, 453, 389], "id": 226, "text": "via:"}]}, {"id": 69, "box": [437, 123, 668, 141], "text": "The Prentice- Hall Corporation System, Inc.", "words": [{"box": [437, 127, 458, 140], "id": 227, "text": "The"}, {"box": [461, 126, 510, 140], "id": 228, "text": "Prentice-"}, {"box": [507, 126, 532, 141], "id": 229, "text": "Hall"}, {"box": [534, 124, 598, 139], "id": 230, "text": "Corporation"}, {"box": [601, 123, 644, 140], "id": 231, "text": "System,"}, {"box": [648, 123, 668, 138], "id": 232, "text": "Inc."}]}, {"id": 70, "box": [443, 159, 616, 181], "text": "TX 3951 U", "words": [{"box": [443, 161, 478, 181], "id": 233, "text": "TX"}, {"box": [496, 161, 577, 178], "id": 234, "text": "3951"}, {"box": [595, 159, 616, 176], "id": 235, "text": "U"}]}, {"id": 71, "box": [444, 920, 487, 935], "text": "Signed:", "words": [{"box": [444, 920, 487, 935], "id": 236, "text": "Signed:"}]}, {"id": 72, "box": [447, 219, 551, 232], "text": "MOTOR CARRIER", "words": [{"box": [447, 219, 493, 230], "id": 237, "text": "MOTOR"}, {"box": [494, 219, 551, 232], "id": 238, "text": "CARRIER"}]}, {"id": 73, "box": [483, 233, 503, 246], "text": "OR", "words": [{"box": [483, 233, 503, 246], "id": 239, "text": "OR"}]}, {"id": 74, "box": [447, 247, 520, 262], "text": "STATUTORY", "words": [{"box": [447, 247, 520, 262], "id": 240, "text": "STATUTORY"}]}, {"id": 75, "box": [447, 278, 507, 293], "text": "Account #", "words": [{"box": [447, 278, 493, 293], "id": 241, "text": "Account"}, {"box": [496, 279, 507, 290], "id": 242, "text": "#"}]}, {"id": 76, "box": [465, 670, 635, 687], "text": "Agent called New York Office", "words": [{"box": [465, 672, 501, 687], "id": 243, "text": "Agent"}, {"box": [504, 672, 539, 686], "id": 244, "text": "called"}, {"box": [542, 672, 567, 686], "id": 245, "text": "New"}, {"box": [570, 670, 597, 684], "id": 246, "text": "York"}, {"box": [601, 670, 635, 685], "id": 247, "text": "Office"}]}, {"id": 77, "box": [490, 792, 529, 806], "text": "Phone", "words": [{"box": [490, 792, 529, 806], "id": 248, "text": "Phone"}]}, {"id": 78, "box": [493, 568, 546, 584], "text": "Case No.", "words": [{"box": [493, 568, 524, 582], "id": 249, "text": "Case"}, {"box": [525, 570, 546, 584], "id": 250, "text": "No."}]}, {"id": 79, "box": [494, 785, 583, 799], "text": "512/478- 4873", "words": [{"box": [494, 785, 551, 799], "id": 251, "text": "512/478-"}, {"box": [552, 786, 583, 799], "id": 252, "text": "4873"}]}, {"id": 80, "box": [494, 841, 576, 856], "text": "PAT HIGGINS", "words": [{"box": [494, 842, 519, 856], "id": 253, "text": "PAT"}, {"box": [522, 841, 576, 856], "id": 254, "text": "HIGGINS"}]}, {"id": 81, "box": [521, 398, 580, 411], "text": "Certified #", "words": [{"box": [521, 398, 567, 411], "id": 255, "text": "Certified"}, {"box": [570, 398, 580, 409], "id": 256, "text": "#"}]}, {"id": 82, "box": [524, 423, 665, 442], "text": "Notice of Mechanic's Lien", "words": [{"box": [524, 427, 559, 441], "id": 257, "text": "Notice"}, {"box": [561, 427, 574, 440], "id": 258, "text": "of"}, {"box": [575, 425, 636, 442], "id": 259, "text": "Mechanic's"}, {"box": [638, 423, 665, 440], "id": 260, "text": "Lien"}]}, {"id": 83, "box": [524, 444, 673, 461], "text": "Notice of Default Jucgment", "words": [{"box": [524, 446, 559, 461], "id": 261, "text": "Notice"}, {"box": [561, 444, 574, 458], "id": 262, "text": "of"}, {"box": [577, 446, 616, 461], "id": 263, "text": "Default"}, {"box": [617, 446, 673, 460], "id": 264, "text": "Jucgment"}]}, {"id": 84, "box": [525, 464, 579, 481], "text": "Subpoena", "words": [{"box": [525, 464, 579, 481], "id": 265, "text": "Subpoena"}]}, {"id": 85, "box": [528, 879, 686, 944], "text": "<unk>", "words": [{"id": 266, "text": "<unk>", "box": [528, 879, 686, 944]}]}, {"id": 86, "box": [546, 240, 556, 255], "text": "x", "words": [{"box": [546, 240, 556, 255], "id": 267, "text": "x"}]}, {"id": 87, "box": [546, 265, 591, 280], "text": "033052", "words": [{"box": [546, 265, 591, 280], "id": 268, "text": "033052"}]}, {"id": 88, "box": [559, 564, 613, 578], "text": "475,592", "words": [{"box": [559, 564, 613, 578], "id": 269, "text": "475,592"}]}, {"id": 89, "box": [708, 817, 722, 892], "text": "92380595", "words": [{"box": [708, 817, 722, 892], "id": 270, "text": "92380595"}]}], "label_entities": [{"entity_id": 0, "label": "question", "word_idx": [193]}, {"entity_id": 1, "label": "question", "word_idx": [4]}, {"entity_id": 2, "label": "question", "word_idx": [5]}, {"entity_id": 3, "label": "question", "word_idx": [103]}, {"entity_id": 4, "label": "question", "word_idx": [6]}, {"entity_id": 5, "label": "answer", "word_idx": [267]}, {"entity_id": 6, "label": "answer", "word_idx": [268]}, {"entity_id": 7, "label": "question", "word_idx": [226]}, {"entity_id": 8, "label": "answer", "word_idx": [188]}, {"entity_id": 9, "label": "question", "word_idx": [77]}, {"entity_id": 10, "label": "question", "word_idx": [78]}, {"entity_id": 11, "label": "question", "word_idx": [87]}, {"entity_id": 12, "label": "answer", "word_idx": [67]}, {"entity_id": 13, "label": "question", "word_idx": [208]}, {"entity_id": 14, "label": "question", "word_idx": [265]}, {"entity_id": 15, "label": "question", "word_idx": [10]}, {"entity_id": 16, "label": "question", "word_idx": [37, 38]}, {"entity_id": 17, "label": "question", "word_idx": [166]}, {"entity_id": 18, "label": "answer", "word_idx": [269]}, {"entity_id": 19, "label": "question", "word_idx": [39]}, {"entity_id": 20, "label": "question", "word_idx": [248]}, {"entity_id": 21, "label": "question", "word_idx": [44]}, {"entity_id": 22, "label": "answer", "word_idx": [120]}, {"entity_id": 23, "label": "question", "word_idx": [236]}, {"entity_id": 24, "label": "header", "word_idx": [126, 127, 128, 129]}, {"entity_id": 25, "label": "answer", "word_idx": [88, 89, 90]}, {"entity_id": 26, "label": "answer", "word_idx": [91, 92, 93, 94, 95, 96, 97, 98, 99, 100, 101, 102]}, {"entity_id": 27, "label": "answer", "word_idx": [104, 105, 106, 107, 108, 109, 110]}, {"entity_id": 28, "label": "question", "word_idx": [237, 238]}, {"entity_id": 29, "label": "question", "word_idx": [239, 240]}, {"entity_id": 30, "label": "question", "word_idx": [241, 242]}, {"entity_id": 31, "label": "answer", "word_idx": [111, 112]}, {"entity_id": 32, "label": "header", "word_idx": [183, 184, 185, 186, 187]}, {"entity_id": 33, "label": "question", "word_idx": [68, 69, 70, 71, 72, 73, 74, 75, 76]}, {"entity_id": 34, "label": "answer", "word_idx": [130, 131, 132, 133, 134, 135]}, {"entity_id": 35, "label": "question", "word_idx": [58, 59, 60, 61, 62, 63, 64, 65, 66]}, {"entity_id": 36, "label": "answer", "word_idx": [217, 218, 219]}, {"entity_id": 37, "label": "question", "word_idx": [136, 137]}, {"entity_id": 38, "label": "question", "word_idx": [191, 192]}, {"entity_id": 39, "label": "question", "word_idx": [224, 225]}, {"entity_id": 40, "label": "question", "word_idx": [255, 256]}, {"entity_id": 41, "label": "question", "word_idx": [79, 80, 81, 82, 83, 84, 85, 86]}, {"entity_id": 42, "label": "question", "word_idx": [202, 203, 204, 205, 206, 207]}, {"entity_id": 43, "label": "question", "word_idx": [209, 210, 211, 212]}, {"entity_id": 44, "label": "question", "word_idx": [257, 258, 259, 260]}, {"entity_id": 45, "label": "question", "word_idx": [261, 262, 263, 264]}, {"entity_id": 46, "label": "answer", "word_idx": [121, 122, 123, 124, 125]}, {"entity_id": 47, "label": "question", "word_idx": [7, 8, 9]}, {"entity_id": 48, "label": "answer", "word_idx": [164, 165]}, {"entity_id": 49, "label": "answer", "word_idx": [113, 114, 115, 116, 117, 118, 119]}, {"entity_id": 50, "label": "question", "word_idx": [249, 250]}, {"entity_id": 51, "label": "question", "word_idx": [11, 12, 13]}, {"entity_id": 52, "label": "answer", "word_idx": [167, 168, 169, 170, 171, 172, 173]}, {"entity_id": 53, "label": "answer", "word_idx": [141, 142, 143, 144, 145, 146, 147, 148]}, {"entity_id": 54, "label": "question", "word_idx": [243, 244, 245, 246, 247]}, {"entity_id": 55, "label": "question", "word_idx": [14, 15, 16, 17]}, {"entity_id": 56, "label": "question", "word_idx": [189, 190]}, {"entity_id": 57, "label": "question", "word_idx": [18, 19, 20]}, {"entity_id": 58, "label": "answer", "word_idx": [174, 175, 176, 177, 178, 179, 180, 181, 182]}, {"entity_id": 59, "label": "answer", "word_idx": [251, 252]}, {"entity_id": 60, "label": "header", "word_idx": [40, 41, 42, 43]}, {"entity_id": 61, "label": "question", "word_idx": [56, 57]}, {"entity_id": 62, "label": "question", "word_idx": [149, 150]}, {"entity_id": 63, "label": "question", "word_idx": [214, 215, 216]}, {"entity_id": 64, "label": "answer", "word_idx": [253, 254]}, {"entity_id": 65, "label": "question", "word_idx": [35, 36]}, {"entity_id": 66, "label": "answer", "word_idx": [138, 139, 140]}], "label_linkings": [[1, 25], [2, 26], [3, 27], [4, 31], [29, 5], [28, 5], [30, 6], [37, 8], [11, 12], [11, 46], [15, 49], [16, 53], [50, 18], [20, 59], [60, 21], [61, 22], [33, 34], [35, 36], [47, 48], [51, 52], [57, 58], [60, 61], [60, 62], [63, 64], [65, 66]], "uid": "92380595", "img": {"fname": "images/92380595.png", "height": 1000, "width": 802}, "ro_linkings": [[0, 1], [1, 25], [2, 26], [3, 41], [4, 42], [5, 31], [6, 44], [7, 43], [8, 45], [9, 15], [10, 37], [11, 38], [12, 8], [13, 16], [14, 61], [15, 10], [15, 71], [16, 32], [17, 62], [18, 24], [19, 35], [20, 21], [20, 56], [21, 22], [21, 83], [22, 23], [23, 18], [23, 58], [24, 33], [25, 2], [26, 27], [27, 28], [28, 29], [29, 3], [30, 48], [31, 63], [32, 14], [32, 39], [33, 4], [34, 0], [34, 69], [35, 17], [36, 49], [38, 7], [39, 61], [40, 54], [41, 30], [42, 5], [43, 50], [44, 11], [45, 46], [46, 47], [47, 77], [48, 19], [49, 51], [50, 76], [51, 67], [52, 55], [53, 40], [54, 34], [56, 57], [57, 58], [57, 82], [58, 59], [58, 84], [59, 4], [61, 80], [62, 68], [63, 64], [64, 65], [65, 66], [66, 78], [67, 81], [68, 36], [69, 70], [70, 72], [71, 85], [72, 73], [73, 74], [74, 86], [75, 87], [76, 12], [77, 79], [78, 88], [79, 13], [80, 9], [81, 20], [82, 83], [83, 84], [84, 4], [86, 75], [87, 48], [88, 6]]}